{
  "project_info": {
    "project_number": "1097219424172",
    "firebase_url": "https://the-streets-will-live-default-rtdb.firebaseio.com",
    "project_id": "the-streets-will-live",
    "storage_bucket": "the-streets-will-live.appspot.com"
  },
  "client": [
    {
      "client_info": {
        "mobilesdk_app_id": "1:1097219424172:android:ff8f007b19ae930c95c409",
        "android_client_info": {
          "package_name": "com.example.toystore"
        }
      },
      "oauth_client": [
        {
          "client_id": "1097219424172-fi061feega0nnvc5j44ilm42tlo97qfl.apps.googleusercontent.com",
          "client_type": 3
        }
      ],
      "api_key": [
        {
          "current_key": "AIzaSyBI3ZWagmQ3G_QqqllTEEpKWNV5x_wjYAQ"
        }
      ],
      "services": {
        "appinvite_service": {
          "other_platform_oauth_client": [
            {
              "client_id": "1097219424172-fi061feega0nnvc5j44ilm42tlo97qfl.apps.googleusercontent.com",
              "client_type": 3
            }
          ]
        }
      }
    },
    {
      "client_info": {
        "mobilesdk_app_id": "1:1097219424172:android:93f9fcf3ec04277695c409",
        "android_client_info": {
          "package_name": "com.example.tswl"
        }
      },
      "oauth_client": [
        {
          "client_id": "1097219424172-fi061feega0nnvc5j44ilm42tlo97qfl.apps.googleusercontent.com",
          "client_type": 3
        }
      ],
      "api_key": [
        {
          "current_key": "AIzaSyBI3ZWagmQ3G_QqqllTEEpKWNV5x_wjYAQ"
        }
      ],
      "services": {
        "appinvite_service": {
          "other_platform_oauth_client": [
            {
              "client_id": "1097219424172-fi061feega0nnvc5j44ilm42tlo97qfl.apps.googleusercontent.com",
              "client_type": 3
            }
          ]
        }
      }
    }
  ],
  "configuration_version": "1"
}